veo/__init__.py
veo2-1767166.928.410.dist-info/licenses/LICENSE
veo2-1767166.928.410.dist-info/METADATA
veo2-1767166.928.410.dist-info/WHEEL
veo2-1767166.928.410.dist-info/top_level.txt
veo2-1767166.928.410.dist-info/RECORD
